docpy/__init__.py
docpy/regexes.py
docpy-0.1.1.data/scripts/docpy
docpy-0.1.1.dist-info/METADATA
docpy-0.1.1.dist-info/WHEEL
docpy-0.1.1.dist-info/top_level.txt
docpy-0.1.1.dist-info/RECORD
