Metadata-Version: 2.1
Name: docpy
Version: 0.1.1
Summary: Python to MD documentation generator
Home-page: https://github.com/chrispyles/docpy
Author: Chris Pyles
Author-email: cpyles@berkeley.edu
License: BSD-3-Clause
Platform: UNKNOWN
Classifier: Programming Language :: Python :: 3
Classifier: License :: OSI Approved :: BSD License
Classifier: Operating System :: OS Independent
